recaptcha_solver_selenium/__init__.py
recaptcha_solver_selenium-0.0.4.dist-info/METADATA
recaptcha_solver_selenium-0.0.4.dist-info/WHEEL
recaptcha_solver_selenium-0.0.4.dist-info/top_level.txt
recaptcha_solver_selenium-0.0.4.dist-info/RECORD
