Metadata-Version: 2.1
Name: recaptcha-solver-selenium
Version: 0.0.4
Summary: A small example package
Home-page: https://github.com/folonidev/recaptcha-solver-selenium
Author: Gabriel Foloni
Project-URL: Homepage, https://github.com/folonidev/recaptcha-solver-selenium
Classifier: Programming Language :: Python :: 3
Classifier: License :: OSI Approved :: MIT License
Classifier: Operating System :: OS Independent
Requires-Python: >=3.6
Requires-Dist: pydub
Requires-Dist: speechrecognition
Requires-Dist: requests
Requires-Dist: selenium
